{
  "trading_relevant": "no",
  "strategy": "other",
  "summary": "Kenneth explains the 4% rule for retirement withdrawals, demonstrating how withdrawing 4% annually from a portfolio while the S&P 500 averages 10% returns can theoretically grow wealth indefinitely. The content focuses on passive buy-and-hold retirement planning with diversified allocations (stocks, bonds, CDs, treasuries, cash) rather than active options trading or premium income strategies.",
  "takeaways": [
    "4% annual withdrawal rate from retirement portfolio",
    "S&P 500 historical average return ~10%",
    "Withdraw less than market gains to maintain account growth",
    "Retirees should diversify beyond 100% stock index funds into bonds, CDs, treasury bills, and cash",
    "Account value can increase even while taking annual withdrawals if market returns exceed withdrawal rate"
  ],
  "strategy_candidates": [],
  "id": "UlKfHGDDP9Y",
  "title": "What is the 4% Rule for investing?",
  "duration": 180
}